{"cik":"58340","entityType":"other","sic":"","sicDescription":"","ownerOrg":null,"insiderTransactionForOwnerExists":0,"insiderTransactionForIssuerExists":0,"name":"LEE FINANCIAL CORP                                      /ADV","tickers":[],"exchanges":[],"ein":"751465685","description":"","website":"","investorWebsite":"","category":"","fiscalYearEnd":"1231","stateOfIncorporation":"TX","stateOfIncorporationDescription":"TX","addresses":{"mailing":{"street1":null,"street2":null,"city":null,"stateOrCountry":null,"zipCode":null,"stateOrCountryDescription":null},"business":{"street1":"12201 MERIT DR STE 530","street2":null,"city":"DALLAS","stateOrCountry":"TX","zipCode":"75251-2261","stateOrCountryDescription":"TX"}},"phone":"9729601001","flags":"","formerNames":[],"filings":{"recent":{"accessionNumber":["9999999997-10-019147","9999999997-09-026133","9999999997-08-044001","9999999997-07-047515","9999999997-06-038445","9999999997-05-017893","9999999997-03-042993","9999999997-03-006236","9999999997-02-012096","9999999997-02-008076"],"filingDate":["2010-08-26","2009-10-01","2008-10-07","2007-10-31","2006-09-11","2005-04-05","2003-11-25","2003-02-25","2002-02-26","2002-02-05"],"reportDate":["","","","","","","","","",""],"acceptanceDateTime":["2010-10-28T11:20:31.000Z","2009-10-29T09:14:02.000Z","2008-10-28T15:33:14.000Z","2007-11-07T20:11:30.000Z","2006-09-13T15:30:21.000Z","2005-04-11T16:26:28.000Z","2003-11-26T09:36:53.000Z","2003-02-28T10:57:20.000Z","2002-02-26T00:00:00.000Z","2002-02-05T00:00:00.000Z"],"act":["40","40","40","40","40","40","","","",""],"form":["ADV-E","ADV-E","ADV-E","ADV-E","ADV-E","ADV-E","ADV-E","ADV-E","ADV-E","ADV-E"],"fileNumber":["801-10722","801-10722","801-10722","801-10722","801-10722","801-10722","801-10722","801-10722","801-10722","801-10722"],"filmNumber":["10032344","09041574","08032832","07008088","06009841","05041474","03052547","03001806","02004044","02006163"],"items":["","","","","","","","","",""],"core_type":["ADV-E","ADV-E","ADV-E","ADV-E","ADV-E","ADV-E","ADV-E","ADV-E","ADV-E","ADV-E"],"size":[1642,1642,1642,1642,1642,1642,1613,1613,1577,1577],"isXBRL":[0,0,0,0,0,0,0,0,0,0],"isInlineXBRL":[0,0,0,0,0,0,0,0,0,0],"primaryDocument":["9999999997-10-019147.paper","9999999997-09-026133.paper","9999999997-08-044001.paper","9999999997-07-047515.paper","9999999997-06-038445.paper","9999999997-05-017893.paper","9999999997-03-042993.paper","9999999997-03-006236.paper","9999999997-02-012096.paper","9999999997-02-008076.paper"],"primaryDocDescription":["AUTO-GENERATED PAPER DOCUMENT","AUTO-GENERATED PAPER DOCUMENT","AUTO-GENERATED PAPER DOCUMENT","AUTO-GENERATED PAPER DOCUMENT","AUTO-GENERATED PAPER DOCUMENT","AUTO-GENERATED PAPER DOCUMENT","AUTO-GENERATED PAPER DOCUMENT","AUTO-GENERATED PAPER DOCUMENT","AUTO-GENERATED PAPER DOCUMENT","AUTO-GENERATED PAPER DOCUMENT"]},"files":[]}}