{"cik":"61597","entityType":"other","sic":"","sicDescription":"","ownerOrg":null,"insiderTransactionForOwnerExists":0,"insiderTransactionForIssuerExists":0,"name":"MAIN STREET MANAGEMENT COMPANY","tickers":[],"exchanges":[],"ein":"060811437","description":"","website":"","investorWebsite":"","category":"","fiscalYearEnd":"1231","stateOfIncorporation":"CT","stateOfIncorporationDescription":"CT","addresses":{"mailing":{"street1":"P.O. BOX 5850","street2":null,"city":"WALLINGFORD","stateOrCountry":"CT","zipCode":"06492-5850","stateOrCountryDescription":"CT"},"business":{"street1":"LIBERTY PLAZA","street2":"101 BARNES RD, STE. 104","city":"WALLINGFORD","stateOrCountry":"CT","zipCode":"06492-7650","stateOrCountryDescription":"CT"}},"phone":"203-265-9778","flags":"","formerNames":[],"filings":{"recent":{"accessionNumber":["9999999997-04-018193","9999999997-04-010047","9999999997-03-007924","9999999997-02-016447"],"filingDate":["2004-04-06","2004-02-27","2003-02-25","2002-02-20"],"reportDate":["2003-12-31","2003-12-31","2002-12-31","2001-12-31"],"acceptanceDateTime":["2004-04-14T15:59:03.000Z","2004-03-16T16:24:56.000Z","2003-03-10T19:06:50.000Z","2002-02-20T00:00:00.000Z"],"act":["","","",""],"form":["X-17A-5/A","X-17A-5","X-17A-5","X-17A-5"],"fileNumber":["008-12925","008-12925","008-12925","008-12925"],"filmNumber":["04016271","04004721","03012264","02005069"],"items":["","","",""],"core_type":["X-17A-5/A","X-17A-5","X-17A-5","X-17A-5"],"size":[2010,2004,2004,1943],"isXBRL":[0,0,0,0],"isInlineXBRL":[0,0,0,0],"primaryDocument":["9999999997-04-018193.paper","9999999997-04-010047.paper","9999999997-03-007924.paper","9999999997-02-016447.paper"],"primaryDocDescription":["AUTO-GENERATED PAPER DOCUMENT","AUTO-GENERATED PAPER DOCUMENT","AUTO-GENERATED PAPER DOCUMENT","AUTO-GENERATED PAPER DOCUMENT"]},"files":[]}}