{"cik":"61514","entityType":"other","sic":"","sicDescription":"","ownerOrg":null,"insiderTransactionForOwnerExists":1,"insiderTransactionForIssuerExists":0,"name":"MAGNUSON HARRY F","tickers":[],"exchanges":[],"ein":null,"description":"","website":"","investorWebsite":"","category":"","fiscalYearEnd":null,"stateOfIncorporation":"","stateOfIncorporationDescription":"","addresses":{"mailing":{"street1":null,"street2":null,"city":null,"stateOrCountry":null,"zipCode":null,"stateOrCountryDescription":null},"business":{"street1":null,"street2":null,"city":null,"stateOrCountry":"","zipCode":null,"stateOrCountryDescription":""}},"phone":null,"flags":"","formerNames":[],"filings":{"recent":{"accessionNumber":["0001401049-08-000026"],"filingDate":["2008-04-10"],"reportDate":["2008-01-23"],"acceptanceDateTime":["2008-04-10T11:41:14.000Z"],"act":["34"],"form":["3"],"fileNumber":["000-53035"],"filmNumber":["08749244"],"items":[""],"core_type":["3"],"size":[3330],"isXBRL":[0],"isInlineXBRL":[0],"primaryDocument":["xslF345X02/primary_doc.xml"],"primaryDocDescription":["PRIMARY DOCUMENT"]},"files":[]}}