{"cik":"56975","entityType":"other","sic":"","sicDescription":"","ownerOrg":null,"insiderTransactionForOwnerExists":0,"insiderTransactionForIssuerExists":0,"name":"VOSS & CO., INC.","tickers":[],"exchanges":[],"ein":"540921080","description":"","website":"","investorWebsite":"","category":"","fiscalYearEnd":"0930","stateOfIncorporation":"VA","stateOfIncorporationDescription":"VA","addresses":{"mailing":{"street1":"P.O. BOX 5097","street2":null,"city":"SPRINGFIELD","stateOrCountry":"VA","zipCode":"22150-5097","stateOrCountryDescription":"VA"},"business":{"street1":"6225 BRANDON AVE.","street2":"SUITE 120","city":"SPRINGFIELD","stateOrCountry":"VA","zipCode":"22150-5097","stateOrCountryDescription":"VA"}},"phone":"703-569-9300","flags":"","formerNames":[],"filings":{"recent":{"accessionNumber":["9999999997-02-060423","9999999997-02-059971"],"filingDate":["2002-12-02","2002-12-02"],"reportDate":["2002-09-30","2002-09-30"],"acceptanceDateTime":["2002-12-12T11:03:23.000Z","2002-12-09T09:24:05.000Z"],"act":["",""],"form":["X-17A-5","FOCUSN"],"fileNumber":["008-17380","008-17380"],"filmNumber":["02053109","02053108"],"items":["",""],"core_type":["X-17A-5","FOCUSN"],"size":[2057,2054],"isXBRL":[0,0],"isInlineXBRL":[0,0],"primaryDocument":["9999999997-02-060423.paper","9999999997-02-059971.paper"],"primaryDocDescription":["AUTO-GENERATED PAPER DOCUMENT","AUTO-GENERATED PAPER DOCUMENT"]},"files":[]}}